csvwrangle/__init__.py
csvwrangle/cli.py
csvwrangle/frame.py
csvwrangle/utils/sysio.py
csvwrangle-0.0.1.dist-info/METADATA
csvwrangle-0.0.1.dist-info/WHEEL
csvwrangle-0.0.1.dist-info/entry_points.txt
csvwrangle-0.0.1.dist-info/top_level.txt
csvwrangle-0.0.1.dist-info/RECORD
